LICENSE
MANIFEST.in
README.md
pyproject.toml
setup.cfg
setup.py
sendero/__init__.py
sendero.egg-info/PKG-INFO
sendero.egg-info/SOURCES.txt
sendero.egg-info/dependency_links.txt
sendero.egg-info/top_level.txt