Metadata-Version: 2.1
Name: sendero
Version: 0.1.0
Summary: sendero - data filtering for humans
Home-page: https://github.com/DanielJDufour/sendero
Download-URL: https://github.com/DanielJDufour/sendero/tarball/download
Author: Daniel J. Dufour
Author-email: daniel.j.dufour@gmail.com
Keywords: data,filter,path
Classifier: Programming Language :: Python :: 3
Classifier: Operating System :: OS Independent
License-File: LICENSE
